docs/Makefile
docs/make.bat
docs/source/conf.py
docs/source/dual_autodiff.ipynb
docs/source/dual_autodiff.rst
docs/source/index.rst
docs/source/modules.rst
docs/source/tutorial.rst
dual_autodiff/__init__.py
dual_autodiff/base.py
dual_autodiff/dual.py
dual_autodiff/functions.py
dual_autodiff/version.py
dual_autodiff_x/README.md
dual_autodiff_x/pyproject.toml
dual_autodiff_x/setup.py
dual_autodiff_x/dual_autodiff/__init__.py
dual_autodiff_x/dual_autodiff/base.py
dual_autodiff_x/dual_autodiff/base.pyx
dual_autodiff_x/dual_autodiff/dual.pyx
dual_autodiff_x/dual_autodiff/functions.pyx
dual_autodiff_x/dual_autodiff/version.pyx
dual_autodiff_x/wheelhouse/dual_autodiff_x-0.0.1b2-cp310-cp310-linux_x86_64.whl
dual_autodiff_x/wheelhouse/dual_autodiff_x-0.0.1b2-cp311-cp311-linux_x86_64.whl
tests/test_dual.py
tests/test_functions.py
dual_autodiff-0.0.post26.dist-info/LICENCE
dual_autodiff-0.0.post26.dist-info/METADATA
dual_autodiff-0.0.post26.dist-info/WHEEL
dual_autodiff-0.0.post26.dist-info/entry_points.txt
dual_autodiff-0.0.post26.dist-info/top_level.txt
dual_autodiff-0.0.post26.dist-info/RECORD
