Metadata-Version: 2.1
Name: dual_autodiff
Version: 0.0.post26
Summary: A Python package for forward-mode automatic differentiation using dual numbers.
Author-email: Raunaq Rai <rsr45@cam.ac.uk>
License: MIT Licence
Project-URL: Documentation, https://your-readthedocs-url-here
Project-URL: Source, https://gitlab.developers.cam.ac.uk/phy/data-intensive-science-mphil/assessments/c1_coursework1/rsr45.git
Project-URL: Issues, https://github.com/yourusername/dual_autodiff/issues
Keywords: automatic differentiation,dual numbers,forward-mode
Classifier: Development Status :: 4 - Beta
Classifier: Intended Audience :: Developers
Classifier: License :: OSI Approved :: MIT License
Classifier: Programming Language :: Python :: 3
Classifier: Topic :: Scientific/Engineering :: Mathematics
Classifier: Topic :: Software Development :: Libraries
Requires-Python: >=3.9
License-File: LICENCE
Requires-Dist: numpy>=1.20.0
Requires-Dist: pytest>=6.0
Requires-Dist: argparse
